LICENSE.txt
MANIFEST.in
Milo revision history.txt
README.md
setup.cfg
setup.py
versioneer.py
ALS.Milo.egg-info/PKG-INFO
ALS.Milo.egg-info/SOURCES.txt
ALS.Milo.egg-info/dependency_links.txt
ALS.Milo.egg-info/entry_points.txt
ALS.Milo.egg-info/requires.txt
ALS.Milo.egg-info/top_level.txt
als/__init__.py
als/milo/__init__.py
als/milo/_version.py
als/milo/miloplot.py
als/milo/qalign.py
als/milo/qimage.py
als/milo/qscan.py
als/milo/version.py
als/milo/version_id.py