Metadata-Version: 2.1
Name: ALS.Milo
Version: 0.15.1
Summary: Setup & analyze data from ALS BL 4.0.2 diffractometer
Home-page: https://bitbucket.org/berkeleylab/als.milo/src/master/
Author: Padraic Shafer
Author-email: pshafer@lbl.gov
License: UNKNOWN
Keywords: CCD RSXD XRMS XRMR x-ray ALS BL4.0.2 diffraction
Platform: UNKNOWN
Classifier: Development Status :: 4 - Beta
Classifier: Intended Audience :: Science/Research
Classifier: Topic :: Scientific/Engineering :: Physics
Classifier: License :: OSI Approved :: BSD License
Classifier: Programming Language :: Python :: 2
Classifier: Programming Language :: Python :: 2.7
Classifier: Operating System :: OS Independent
Classifier: Environment :: Console
